problem_designer/__init__.py
problem_designer/cli/__init__.py
problem_designer/cli/__main__.py
problem_designer/cli/cmd/__init__.py
problem_designer/cli/cmd/documentation.py
problem_designer/cli/cmd/generate.py
problem_designer/cli/cmd/list.py
problem_designer/cli/services/__init__.py
problem_designer/cli/services/generator.py
problem_designer/cli/services/helper.py
problem_designer/cli/services/spec.py
problem_designer/cli/typedef.py
problem_designer/plugin/__init__.py
problem_designer/plugin/helper.py
problem_designer/plugin/manager.py
problem_designer/plugin/typedef.py
problem_designer/problems/scheduling/__init__.py
problem_designer/problems/scheduling/constants/__init__.py
problem_designer/problems/scheduling/constants/characteristic.py
problem_designer/problems/scheduling/constants/objective.py
problem_designer/problems/scheduling/constants/parameter.py
problem_designer/problems/scheduling/flow_shop/__init__.py
problem_designer/problems/scheduling/flow_shop/generated_problem.py
problem_designer/problems/scheduling/flow_shop/generator.py
problem_designer/problems/scheduling/flow_shop/output.py
problem_designer/problems/scheduling/flow_shop/spec.py
problem_designer/problems/scheduling/generator/__init__.py
problem_designer/problems/scheduling/generator/helper.py
problem_designer/problems/scheduling/generator/typedef.py
problem_designer/problems/scheduling/job_shop/__init__.py
problem_designer/problems/scheduling/job_shop/generated_problem.py
problem_designer/problems/scheduling/job_shop/generator.py
problem_designer/problems/scheduling/job_shop/output.py
problem_designer/problems/scheduling/job_shop/spec.py
problem_designer/problems/scheduling/open_shop/__init__.py
problem_designer/problems/scheduling/open_shop/generated_problem.py
problem_designer/problems/scheduling/open_shop/generator.py
problem_designer/problems/scheduling/open_shop/output.py
problem_designer/problems/scheduling/open_shop/spec.py
problem_designer/typedef/__init__.py
problem_designer-0.1.2.dist-info/METADATA
problem_designer-0.1.2.dist-info/WHEEL
problem_designer-0.1.2.dist-info/entry_points.txt
problem_designer-0.1.2.dist-info/RECORD
