Metadata-Version: 2.1
Name: problem_designer
Version: 0.1.2
Summary: A package for designing and distributing problems
Author: Dominik Falkner
Author-email: dominik.falkner@risc-software.at
Requires-Python: >=3.10,<4.0
Classifier: Programming Language :: Python :: 3
Classifier: Programming Language :: Python :: 3.10
Classifier: Programming Language :: Python :: 3.11
Classifier: Programming Language :: Python :: 3.12
Requires-Dist: numpy (>=1.24.1,<2.0.0)
Requires-Dist: pluggy (>=1.0.0,<2.0.0)
Requires-Dist: pydantic (>=1.10.4,<2.0.0)
Requires-Dist: pydantic-cli (>=4.3.0,<5.0.0)
Requires-Dist: pyjson5 (>=1.6.4,<2.0.0)
Requires-Dist: rich (>=13.3.1,<14.0.0)
Requires-Dist: scikit-learn (>=1.2.1,<2.0.0)
